lihil_mcp/README.md
lihil_mcp/__init__.py
lihil_mcp/config.py
lihil_mcp/decorators.py
lihil_mcp/server.py
lihil_mcp/types.py
lihil_mcp-0.1.0.dist-info/METADATA
lihil_mcp-0.1.0.dist-info/WHEEL
lihil_mcp-0.1.0.dist-info/licenses/LICENSE
lihil_mcp-0.1.0.dist-info/RECORD
